LICENSE
MANIFEST.in
README.rst
setup.py
WSGIT.egg-info/PKG-INFO
WSGIT.egg-info/SOURCES.txt
WSGIT.egg-info/dependency_links.txt
WSGIT.egg-info/entry_points.txt
WSGIT.egg-info/requires.txt
WSGIT.egg-info/top_level.txt
wsgit/__init__.py
wsgit/request.py
wsgit/server.py
wsgit/wsgi.py