Metadata-Version: 1.1
Name: WSGIT
Version: 0.3.0
Summary: WSGI Server on TCP
Home-page: UNKNOWN
Author: Seungyeon Joshua Kim(Acuros)
Author-email: acuroskr@gmail.com
License: MIT License
Platform: UNKNOWN
Classifier: Development Status :: 2 - Pre-Alpha
Classifier: Intended Audience :: Developers
Classifier: License :: OSI Approved :: MIT License
Classifier: Operating System :: OS Independent
Classifier: Programming Language :: Python :: 2.6
Classifier: Programming Language :: Python :: 2.7
Classifier: Topic :: Internet :: WWW/HTTP :: WSGI
Classifier: Topic :: Internet :: WWW/HTTP :: WSGI :: Server
